oasis_certs/__init__.py
oasis_certs/admin.py
oasis_certs/admin_views.py
oasis_certs/apps.py
oasis_certs/models.py
oasis_certs/urls.py
oasis_certs/api/__init__.py
oasis_certs/api/serializers/__init__.py
oasis_certs/api/serializers/certificate.py
oasis_certs/api/services/__init__.py
oasis_certs/api/services/oasis_certs.py
oasis_certs/api/services/oasis_cycle.py
oasis_certs/lib/__init__.py
oasis_certs/lib/choices/__init__.py
oasis_certs/lib/choices/category.py
oasis_certs/lib/choices/cycle_type.py
oasis_certs/lib/cursors/__init__.py
oasis_certs/lib/cursors/cursor.py
oasis_certs/lib/managers/__init__.py
oasis_certs/lib/managers/certificate.py
oasis_certs/locale/es/LC_MESSAGES/django.mo
oasis_certs/locale/es/LC_MESSAGES/django.po
oasis_certs/migrations/0001_initial.py
oasis_certs/migrations/0002_rename_certificates_certificate.py
oasis_certs/migrations/0003_alter_certificate_options_and_more.py
oasis_certs/migrations/0004_certificate_period_type.py
oasis_certs/migrations/0005_remove_certificate_period_type_certificate_closed_and_more.py
oasis_certs/migrations/0006_rename_legend_certificate_body_text.py
oasis_certs/migrations/0007_remove_certificate_unq_certificates_key_and_more.py
oasis_certs/migrations/0008_certificate_customer_type_alter_certificate_category.py
oasis_certs/migrations/0009_certificate_signed_alter_certificate_cycle_type.py
oasis_certs/migrations/0010_alter_certificate_footer_text.py
oasis_certs/migrations/0011_certificatefile.py
oasis_certs/migrations/0012_alter_certificatefile_period_and_more.py
oasis_certs/migrations/__init__.py
oasis_certs/static/oasis_certs/css/certs_base_style.css
oasis_certs/static/oasis_certs/css/certs_cells.css
oasis_certs/static/oasis_certs/img/logo.png
oasis_certs/templates/mail/send_certificate.txt
oasis_certs/templates/oasis_certs/certs_base_template.html
oasis_certs/templates/oasis_certs/coffee_sales_template.html
oasis_certs/templates/oasis_certs/contribution_balance_template.html
django_oasis4_certs-1.0.2.dist-info/LICENSE
django_oasis4_certs-1.0.2.dist-info/METADATA
django_oasis4_certs-1.0.2.dist-info/WHEEL
django_oasis4_certs-1.0.2.dist-info/top_level.txt
django_oasis4_certs-1.0.2.dist-info/RECORD
