Metadata-Version: 2.1
Name: django-oasis4-certs
Version: 1.0.2
Summary: Certificate generator for Django from OASIS4©
Author-email: Mario Cerón <mario.ceron@cqinversiones.co>
License: CQ INVERSIONES S.A.S.
Keywords: django,zibanu,library
Classifier: License :: Other/Proprietary License
Classifier: Programming Language :: Python :: 3.9
Classifier: Development Status :: 5 - Production/Stable
Classifier: Framework :: Django
Classifier: Framework :: Django :: 4.1
Classifier: Environment :: Web Environment
Classifier: Operating System :: OS Independent
Classifier: Topic :: Internet :: WWW/HTTP
Requires-Python: >=3.9
License-File: LICENSE
Requires-Dist: Django (>=4.1)
Requires-Dist: djangorestframework
Requires-Dist: xhtml2pdf
Requires-Dist: zibanu-django
Requires-Dist: django-oasis4
Requires-Dist: django-oasis4-auth
